mortal_build/__init__.py
mortal_build/build_ext_script.cpython-310-x86_64-linux-gnu.so
mortal_build/build_fastapi.cpython-310-x86_64-linux-gnu.so
mortal_build/build_main.cpython-310-x86_64-linux-gnu.so
mortal_build/build_send.cpython-310-x86_64-linux-gnu.so
mortal_build/build_wheel_script.cpython-310-x86_64-linux-gnu.so
mortal_build/setup_ext_template.j2
mortal_build/setup_wheel_template.j2
mortal_build-4.6.0.dist-info/METADATA
mortal_build-4.6.0.dist-info/WHEEL
mortal_build-4.6.0.dist-info/entry_points.txt
mortal_build-4.6.0.dist-info/top_level.txt
mortal_build-4.6.0.dist-info/RECORD
